qrcodelib.py
su_cs114_projectlibs-0.0.2.dist-info/LICENSE
su_cs114_projectlibs-0.0.2.dist-info/METADATA
su_cs114_projectlibs-0.0.2.dist-info/WHEEL
su_cs114_projectlibs-0.0.2.dist-info/top_level.txt
su_cs114_projectlibs-0.0.2.dist-info/RECORD
